cerberus/__init__.py
cerberus/config.yaml
cerberus/start_cerberus.py
cerberus/database/__init__.py
cerberus/database/client.py
cerberus/inspect/__init__.py
cerberus/inspect/inspect.py
cerberus/invoke/__init__.py
cerberus/invoke/command.py
cerberus/kubernetes/__init__.py
cerberus/kubernetes/client.py
cerberus/prometheus/__init__.py
cerberus/prometheus/client.py
cerberus/server/__init__.py
cerberus/server/server.py
cerberus/slack/__init__.py
cerberus/slack/slack_client.py
cerberus_client-1.0.0.dist-info/LICENSE
cerberus_client-1.0.0.dist-info/METADATA
cerberus_client-1.0.0.dist-info/WHEEL
cerberus_client-1.0.0.dist-info/entry_points.txt
cerberus_client-1.0.0.dist-info/top_level.txt
cerberus_client-1.0.0.dist-info/RECORD
