Metadata-Version: 2.1
Name: cerberus-client
Version: 1.0.0
Summary: Guardian of Kubernetes and OpenShift Clusters
Home-page: https://github.com/openshift-scale/cerberus
Author: Naga Ravi Chaitanya Elluri
Author-email: nelluri@redhat.com
License: mit
Platform: UNKNOWN
Classifier: Development Status :: 4 - Beta
Classifier: Programming Language :: Python
Requires-Dist: setuptools
Requires-Dist: PyYAML
Requires-Dist: requests
Requires-Dist: kubernetes
Requires-Dist: datetime
Requires-Dist: configparser
Requires-Dist: slackclient
Requires-Dist: pyfiglet
Requires-Dist: prometheus-api-client
